src/__init__.py
src/main.py
src/api/__init__.py
src/api/server.py
src/generators/__init__.py
src/generators/image_editor.py
src/generators/image_generator.py
src/generators/mock_image_generator.py
src/generators/prompt_generator.py
src/plugins/__init__.py
src/plugins/art_style.py
src/plugins/holiday_fact.py
src/plugins/lora.py
src/plugins/nearest_holiday.py
src/plugins/time_of_day.py
src/utils/__init__.py
src/utils/cli.py
src/utils/config.py
src/utils/embeddings.py
src/utils/error_handler.py
src/utils/logging_config.py
src/utils/memory_manager.py
src/utils/metrics.py
src/utils/plugin_manager.py
src/utils/s3_storage.py
src/utils/storage.py
src/utils/troubleshoot.py
dreamgen-1.0.1.dist-info/METADATA
dreamgen-1.0.1.dist-info/WHEEL
dreamgen-1.0.1.dist-info/entry_points.txt
dreamgen-1.0.1.dist-info/RECORD
