Metadata-Version: 2.4
Name: dreamgen
Version: 1.0.1
Summary: Generate unlimited AI images locally with no subscriptions - your machine dreams with you
Project-URL: Homepage, https://github.com/killerapp/dreamgen
Project-URL: Documentation, https://github.com/killerapp/dreamgen#readme
Project-URL: Repository, https://github.com/killerapp/dreamgen
Project-URL: Issues, https://github.com/killerapp/dreamgen/issues
Author-email: Vaski <vaski@example.com>
License: MIT
Keywords: ai,art,cli,creative,dreams,flux,image-generation,local,ollama
Classifier: Development Status :: 4 - Beta
Classifier: Environment :: Console
Classifier: Intended Audience :: Developers
Classifier: Intended Audience :: End Users/Desktop
Classifier: License :: OSI Approved :: MIT License
Classifier: Programming Language :: Python :: 3
Classifier: Programming Language :: Python :: 3.11
Classifier: Programming Language :: Python :: 3.12
Classifier: Topic :: Multimedia :: Graphics
Classifier: Topic :: Scientific/Engineering :: Artificial Intelligence
Classifier: Topic :: Software Development :: Libraries :: Python Modules
Requires-Python: >=3.11
Requires-Dist: accelerate>=1.3.0
Requires-Dist: aiofiles>=23.0.0
Requires-Dist: diffusers>=0.29.0
Requires-Dist: fastapi>=0.100.0
Requires-Dist: huggingface-hub[inference]>=0.20.0
Requires-Dist: ollama>=0.4.7
Requires-Dist: peft>=0.7.0
Requires-Dist: pillow>=10.0.0
Requires-Dist: protobuf>=5.29.3
Requires-Dist: python-dotenv>=1.0.0
Requires-Dist: python-multipart>=0.0.6
Requires-Dist: rich>=13.0.0
Requires-Dist: safetensors>=0.4.2
Requires-Dist: sentencepiece>=0.2.0
Requires-Dist: shellingham>=1.5.0
Requires-Dist: torch==2.6.0+cu124
Requires-Dist: torchaudio==2.6.0+cu124
Requires-Dist: torchvision==0.21.0+cu124
Requires-Dist: transformers>=4.30.0
Requires-Dist: typer>=0.9.0
Requires-Dist: uvicorn[standard]>=0.23.0
Requires-Dist: websockets>=12.0
Provides-Extra: dev
Requires-Dist: black>=23.0.0; extra == 'dev'
Requires-Dist: build>=1.0.0; extra == 'dev'
Requires-Dist: isort>=5.12.0; extra == 'dev'
Requires-Dist: pylint>=2.17.0; extra == 'dev'
Requires-Dist: pytest-asyncio>=0.21.0; extra == 'dev'
Requires-Dist: pytest>=7.4.0; extra == 'dev'
Requires-Dist: python-semantic-release>=9.0.0; extra == 'dev'
